<?xml version="1.0" encoding="UTF-8"?>
<objects serializationModel="Studio.02.02.00">
	<object class="AudioFile" id="{af0288e5-5ae8-493d-8034-644650f7d127}">
		<property name="assetPath">
			<value>FX/PuzzleStoneHeart/HeartCoupLeger_2.wav</value>
		</property>
		<property name="frequencyInKHz">
			<value>44.0999985</value>
		</property>
		<property name="channelCount">
			<value>2</value>
		</property>
		<property name="length">
			<value>0.048072562358276644</value>
		</property>
		<relationship name="masterAssetFolder">
			<destination>{d5ae0bb6-a231-402a-ab49-cbb9acd8f217}</destination>
		</relationship>
	</object>
</objects>
